gpglock/__init__.py
gpglock/__main__.py
gpglock/cli.py
gpglock/core.py
gpglock/utils/__init__.py
gpglock/utils/console_logging_formatter.py
gpglock/utils/file_system.py
gpglock/utils/gpg_wrapper.py
gpglock/utils/hash.py
gpglock-0.7.0.dist-info/LICENSE
gpglock-0.7.0.dist-info/METADATA
gpglock-0.7.0.dist-info/WHEEL
gpglock-0.7.0.dist-info/entry_points.txt
gpglock-0.7.0.dist-info/RECORD
